apt_select/__init__.py
apt_select/__main__.py
apt_select/apt.py
apt_select/arguments.py
apt_select/mirrors.py
apt_select/utils.py
apt_select-2.2.1.dist-info/LICENSE
apt_select-2.2.1.dist-info/METADATA
apt_select-2.2.1.dist-info/WHEEL
apt_select-2.2.1.dist-info/entry_points.txt
apt_select-2.2.1.dist-info/top_level.txt
apt_select-2.2.1.dist-info/RECORD
